langpy/__init__.py
langpy/__main__.py
langpy/cli/__init__.py
langpy/cli/main.py
langpy/cli/messages.py
langpy/cli/transpile/__init__.py
langpy/cli/transpile/imports.py
langpy/cli/transpile/resolver.py
langpy/cli/transpile/transpiler.py
langpy/cli/transpile/tree.py
langpy/core/__init__.py
langpy/core/importer.py
langpy/core/rebuilder.py
langpy/core/tokenizer.py
langpy/core/transpiler.py
langpy/core/lexicon/__init__.py
langpy/core/lexicon/base.py
langpy/core/lexicon/es.py
langpy/core/lexicon/fr.py
langpy/core/lexicon/pt.py
langpy-0.1.4.dist-info/licenses/LICENSE
langpy-0.1.4.dist-info/METADATA
langpy-0.1.4.dist-info/WHEEL
langpy-0.1.4.dist-info/entry_points.txt
langpy-0.1.4.dist-info/top_level.txt
langpy-0.1.4.dist-info/RECORD
