Metadata-Version: 2.4
Name: LangPy
Version: 0.1.4
Summary: Write Python code using keywords in your native language
Author-email: Esteban Salgado <contact@intorandom.com>
License: # Released under MIT License
Project-URL: Homepage, https://langpy.intorandom.com/
Project-URL: Issues, https://github.com/intoRandom/LangPy/issues
Keywords: python,transpiler,lexer,i18n,spanish,portuguese,french,multilingual
Classifier: Programming Language :: Python :: 3
Classifier: Programming Language :: Python :: 3.10
Classifier: Programming Language :: Python :: 3.11
Classifier: Programming Language :: Python :: 3.12
Classifier: Operating System :: OS Independent
Requires-Python: >=3.10
License-File: LICENSE
Dynamic: license-file
